LICENSE.txt
README
setup.cfg
setup.py
qtooth/Makefile
qtooth/__init__.py
qtooth/blescan.py
qtooth/bluez-src.tgz
qtooth/btle.py
qtooth/get_services.py
qtooth/qtooth-helper.c
qtooth/scan_fuzz.py
qtooth/scanner.py
qtooth/sensortag.py
qtooth/thingy52.py
qtooth/uuids.json
qtooth/version.h
qtooth.egg-info/PKG-INFO
qtooth.egg-info/SOURCES.txt
qtooth.egg-info/dependency_links.txt
qtooth.egg-info/entry_points.txt
qtooth.egg-info/top_level.txt