Metadata-Version: 2.1
Name: qtooth
Version: 1.3.2
Summary: Python module for interfacing with BLE devices through Bluez
Home-page: https://github.com/IanHarvey/bluepy
Download-URL: https://github.com/IanHarvey/bluepy/tarball/v/1.3.2
Author: Ian Harvey
Author-email: website-contact@fenditton.org
License: UNKNOWN
Keywords: Bluetooth,Bluetooth Smart,BLE,Bluetooth Low Energy
Platform: UNKNOWN
Classifier: Programming Language :: Python :: 2.7
Classifier: Programming Language :: Python :: 3.3
Classifier: Programming Language :: Python :: 3.4
License-File: LICENSE.txt
